ragie/__init__.py
ragie/_hooks/__init__.py
ragie/_hooks/registration.py
ragie/_hooks/sdkhooks.py
ragie/_hooks/types.py
ragie/_version.py
ragie/authenticators.py
ragie/basesdk.py
ragie/connections.py
ragie/documents.py
ragie/entities.py
ragie/httpclient.py
ragie/models/__init__.py
ragie/models/accesstokencredentials.py
ragie/models/agent_hopps_models_models_usage.py
ragie/models/answer.py
ragie/models/answerstep.py
ragie/models/asyncdocumentmetadataupdate.py
ragie/models/audiomodalitydata.py
ragie/models/authenticatorconfluenceconnection.py
ragie/models/authenticatordropboxconnection.py
ragie/models/authenticatorgmailconnection.py
ragie/models/authenticatorgoogledriveconnection.py
ragie/models/authenticatorhubspotconnection.py
ragie/models/authenticatorjiraconnection.py
ragie/models/authenticatorlist.py
ragie/models/authenticatornotionconnection.py
ragie/models/authenticatoronedriveconnection.py
ragie/models/authenticatorsalesforceconnection.py
ragie/models/authenticatorsharepointconnection.py
ragie/models/authenticatorslackconnection.py
ragie/models/backblazecredentials.py
ragie/models/basegetauthenticator.py
ragie/models/bucketdata.py
ragie/models/codeinterpreterevidence.py
ragie/models/codeinterpreteroutput.py
ragie/models/codeinterpreteroutputlogs.py
ragie/models/codestep.py
ragie/models/confluencedata.py
ragie/models/connection.py
ragie/models/connectionbase.py
ragie/models/connectionlimitparams.py
ragie/models/connectionlist.py
ragie/models/connectionstats.py
ragie/models/connectorsource.py
ragie/models/connectorsourcetypeinfo.py
ragie/models/createauthenticatorconnection.py
ragie/models/createauthenticatorconnectionop.py
ragie/models/createauthenticatorop.py
ragie/models/createdocumentfromurlparams.py
ragie/models/createdocumentparams.py
ragie/models/createdocumentrawparams.py
ragie/models/creategoogleauthenticator.py
ragie/models/createinstructionparams.py
ragie/models/createpartitionparams.py
ragie/models/createwebhookendpointpayload.py
ragie-1.15.1.dist-info/METADATA
ragie-1.15.1.dist-info/WHEEL
ragie-1.15.1.dist-info/RECORD
